mltrainer_checker/__init__.py
mltrainer_checker/copy_weights.py
mltrainer_checker/covert_dataloader.py
mltrainer_checker/pipeline.py
mltrainer_checker/trainer_checker.py
mltrainer_checker/utils.py
mltrainer_checker-0.16.dist-info/LICENSE
mltrainer_checker-0.16.dist-info/METADATA
mltrainer_checker-0.16.dist-info/WHEEL
mltrainer_checker-0.16.dist-info/top_level.txt
mltrainer_checker-0.16.dist-info/RECORD
