Metadata-Version: 2.1
Name: mltrainer-checker
Version: 0.16
Summary: A tool to validate machine learning models implemented on different machine learning platforms to ensure they are working correctly.
Home-page: https://github.com/hiendang7613/MLTrainerChecker
Author: hiendang7613
Author-email: dvhqnn1@gmail.com
License-File: LICENSE
